powerpoint/__init__.py
powerpoint/chart_manager.py
powerpoint/presentation_manager.py
powerpoint/server.py
powerpoint/vision_manager.py
iflow_mcp_powerpoint-0.1.0.dist-info/METADATA
iflow_mcp_powerpoint-0.1.0.dist-info/WHEEL
iflow_mcp_powerpoint-0.1.0.dist-info/entry_points.txt
iflow_mcp_powerpoint-0.1.0.dist-info/licenses/LICENSE
iflow_mcp_powerpoint-0.1.0.dist-info/RECORD
