Metadata-Version: 2.4
Name: iflow-mcp_powerpoint
Version: 0.1.0
Summary: A MCP server project that creates powerpoint presentations
Author-email: Russell Ashby <158164671+supercurses@users.noreply.github.com>
License-File: LICENSE
Requires-Python: >=3.12
Requires-Dist: mcp>=1.3.0
Requires-Dist: pillow>=11.1.0
Requires-Dist: python-pptx>=1.0.2
Requires-Dist: requests>=2.32.3
Requires-Dist: together>=1.4.1
